LICENSE
README.md
setup.py
lomas_server/__init__.py
lomas_server/app.py
lomas_server/constants.py
lomas_server/mongodb_admin.py
lomas_server/mongodb_admin_cli.py
lomas_server/uvicorn_serve.py
lomas_server.egg-info/PKG-INFO
lomas_server.egg-info/SOURCES.txt
lomas_server.egg-info/dependency_links.txt
lomas_server.egg-info/requires.txt
lomas_server.egg-info/top_level.txt
lomas_server/admin_database/__init__.py
lomas_server/admin_database/admin_database.py
lomas_server/admin_database/constants.py
lomas_server/admin_database/factory.py
lomas_server/admin_database/mongodb_database.py
lomas_server/admin_database/utils.py
lomas_server/admin_database/yaml_database.py
lomas_server/administration/__init__.py
lomas_server/administration/tests/__init__.py
lomas_server/administration/tests/test_streamlit_app.py
lomas_server/administration/tests/test_streamlit_app_page_b.py
lomas_server/administration/tests/utils.py
lomas_server/data_connector/__init__.py
lomas_server/data_connector/data_connector.py
lomas_server/data_connector/factory.py
lomas_server/data_connector/in_memory_connector.py
lomas_server/data_connector/path_connector.py
lomas_server/data_connector/s3_connector.py
lomas_server/dp_queries/__init__.py
lomas_server/dp_queries/dp_querier.py
lomas_server/dp_queries/dummy_dataset.py
lomas_server/dp_queries/dp_libraries/__init__.py
lomas_server/dp_queries/dp_libraries/diffprivlib.py
lomas_server/dp_queries/dp_libraries/factory.py
lomas_server/dp_queries/dp_libraries/opendp.py
lomas_server/dp_queries/dp_libraries/smartnoise_sql.py
lomas_server/dp_queries/dp_libraries/smartnoise_synth.py
lomas_server/dp_queries/dp_libraries/utils.py
lomas_server/routes/__init__.py
lomas_server/routes/middlewares.py
lomas_server/routes/routes_admin.py
lomas_server/routes/routes_dp.py
lomas_server/routes/utils.py
lomas_server/tests/__init__.py
lomas_server/tests/constants.py
lomas_server/tests/test_api.py
lomas_server/tests/test_api_diffprivlib.py
lomas_server/tests/test_api_smartnoise_synth.py
lomas_server/tests/test_collection_models.py
lomas_server/tests/test_dummy_generation.py
lomas_server/tests/test_mongodb_admin.py
lomas_server/tests/test_mongodb_admin_cli.py
