Metadata-Version: 2.2
Name: lomas-server
Version: 0.4.1
Summary: Lomas server.
Home-page: https://github.com/dscc-admin-ch/lomas/
Author: Data Science Competence Center, Swiss Federal Statistical Office
Author-email: dscc@bfs.admin.ch
License: MIT
Classifier: Development Status :: 4 - Beta
Classifier: Intended Audience :: Developers
Classifier: Intended Audience :: Science/Research
Classifier: License :: OSI Approved :: MIT License
Classifier: Natural Language :: English
Classifier: Programming Language :: Python :: 3.11
Classifier: Programming Language :: Python :: 3.12
Classifier: Topic :: Software Development :: Libraries
Classifier: Topic :: Software Development :: Libraries :: Python Modules
Classifier: Topic :: Scientific/Engineering
Classifier: Topic :: Security
Requires-Python: >=3.11, <3.13
License-File: LICENSE
Requires-Dist: boto3==1.34.115
Requires-Dist: httpx==0.27.0
Requires-Dist: jax==0.4.31
Requires-Dist: jaxlib==0.4.31
Requires-Dist: lomas-core==0.4.1
Requires-Dist: opentelemetry-instrumentation-fastapi>=0.50b0
Requires-Dist: opentelemetry-instrumentation-pymongo>=0.50b0
Requires-Dist: packaging==24.1
Requires-Dist: pyaml==23.9.5
Requires-Dist: pydantic==2.8.2
Requires-Dist: smartnoise-sql==1.0.4
Requires-Dist: uvicorn==0.29.0
Dynamic: author
Dynamic: author-email
Dynamic: classifier
Dynamic: description
Dynamic: description-content-type
Dynamic: home-page
Dynamic: license
Dynamic: requires-dist
Dynamic: requires-python
Dynamic: summary
